README.rst
setup.cfg
setup.py
rafproject.egg-info/PKG-INFO
rafproject.egg-info/SOURCES.txt
rafproject.egg-info/dependency_links.txt
rafproject.egg-info/not-zip-safe
rafproject.egg-info/requires.txt
rafproject.egg-info/top_level.txt
src/__init__.py
src/raf/__init__.py
src/raf/3rdparty/__init__.py
src/raf/python/__init__.py
src/raf/python/setup.py
src/raf/python/raf/__init__.py
src/raf/python/raf/_lib.py
src/raf/python/raf/build.py
src/raf/python/raf/_core/__init__.py
src/raf/python/raf/_core/backends.py
src/raf/python/raf/_core/cacher.py
src/raf/python/raf/_core/core_utils.py
src/raf/python/raf/_core/device.py
src/raf/python/raf/_core/executor.py
src/raf/python/raf/_core/global_scope.py
src/raf/python/raf/_core/ir_ext.py
src/raf/python/raf/_core/module.py
src/raf/python/raf/_core/ndarray.py
src/raf/python/raf/_core/value.py
src/raf/python/raf/_core/vm.py
src/raf/python/raf/_core/vm_debug.py
src/raf/python/raf/_ffi/__init__.py
src/raf/python/raf/_ffi/analysis/__init__.py
src/raf/python/raf/_ffi/analysis/_internal.py
src/raf/python/raf/_ffi/backend/__init__.py
src/raf/python/raf/_ffi/backend/cudnn/__init__.py
src/raf/python/raf/_ffi/backend/cudnn/_internal.py
src/raf/python/raf/_ffi/binding/__init__.py
src/raf/python/raf/_ffi/binding/_internal.py
src/raf/python/raf/_ffi/build_info/__init__.py
src/raf/python/raf/_ffi/build_info/_internal.py
src/raf/python/raf/_ffi/cache/__init__.py
src/raf/python/raf/_ffi/cache/_internal.py
src/raf/python/raf/_ffi/device/__init__.py
src/raf/python/raf/_ffi/device/_internal.py
src/raf/python/raf/_ffi/device_api/__init__.py
src/raf/python/raf/_ffi/device_api/_make/__init__.py
src/raf/python/raf/_ffi/device_api/_make/_internal.py
src/raf/python/raf/_ffi/distributed/__init__.py
src/raf/python/raf/_ffi/distributed/_internal.py
src/raf/python/raf/_ffi/distributed/communicator/__init__.py
src/raf/python/raf/_ffi/distributed/communicator/_make/__init__.py
src/raf/python/raf/_ffi/distributed/communicator/_make/_internal.py
src/raf/python/raf/_ffi/executor/__init__.py
src/raf/python/raf/_ffi/executor/_internal.py
src/raf/python/raf/_ffi/ir/__init__.py
src/raf/python/raf/_ffi/ir/_internal.py
src/raf/python/raf/_ffi/ir/_make/__init__.py
